Assignment_4/.v files/assign4_problem4_state_diagram_implementation.v
module state_diagram_implementation (input clk, input reset, input P_A, input P_B, output reg O);

    reg [1:0] state;
    reg [1:0] next_state;
    
    parameter STATE_0 = 2'b00;
    parameter STATE_1 = 2'b01;
    parameter STATE_2 = 2'b10;
    parameter STATE_3 = 2'b11;

    always @(posedge clk or posedge reset) begin
        if (reset) begin
            state <= STATE_0;
            O <= 1'b0;
        end else begin
            state <= next_state;
            O <= (next_state == STATE_1);
        end
    end
    
    always @(*) begin
        case (state)
            STATE_0: begin
                case ({P_A, P_B})
                    2'b00: next_state = STATE_0;
                    2'b01: next_state = STATE_1;
                    2'b10: next_state = STATE_2;
                    2'b11: next_state = STATE_3;
                endcase
            end
            STATE_1: begin
                case ({P_A, P_B})
                    2'b00: next_state = STATE_1;
                    2'b01: next_state = STATE_2;
                    2'b10: next_state = STATE_3;
                    2'b11: next_state = STATE_0;
                endcase
            end
            STATE_2: begin
                case ({P_A, P_B})
                    2'b00: next_state = STATE_2;
                    2'b01: next_state = STATE_3;
                    2'b10: next_state = STATE_0;
                    2'b11: next_state = STATE_1;
                endcase
            end
            STATE_3: begin
                case ({P_A, P_B})
                    2'b00: next_state = STATE_3;
                    2'b01: next_state = STATE_0;
                    2'b10: next_state = STATE_1;
                    2'b11: next_state = STATE_2;
                endcase
            end
            default: next_state = STATE_0;
        endcase
    end

endmodule

Assignment_4/Testbench/assign4_problem4_state_diagram_implementation_tb.v
module state_diagram_implementation_tb;

    // Testbench signals
    reg clk;
    reg reset;
    reg P_A;
    reg P_B;
    wire O;
    reg [8*24-1:0] name;
    state_diagram_implementation uut (.clk(clk), .reset(reset), .P_A(P_A), .P_B(P_B), .O(O));
    
    always #5 clk = ~clk;
    
    integer N_PA, N_PB;
    integer expected_value;
    integer cycle_count;
    
    initial begin
        name = " Kunwar Arpit Singh 22185";
        $display("Kunwar Arpit Singh");
        $dumpfile("assign4_problem4_state_diagram_implementation.vcd");
        $dumpvars(1, state_diagram_implementation_tb);
        $display("Kunwar Arpit Singh");

        clk = 0;
        reset = 1;
        P_A = 0;
        P_B = 0;
        N_PA = 0;
        N_PB = 0;
        cycle_count = 0;
        
        #10;
        reset = 0;
        
        $display("| Cycle | P_A | P_B | N(P_A) | N(P_B) | 2*N(P_A)+N(P_B) | mod4 | O | Expected |");
        $display("-------------------------------------------------------------------------------");
        
        test_cycle(0, 0);
        test_cycle(1, 1);
        test_cycle(1, 0);
        test_cycle(0, 1);
        
        test_cycle(1, 1);
        test_cycle(0, 0);
        test_cycle(1, 0);
        test_cycle(0, 1);
        
        #20;
        $finish;
    end
    
    task test_cycle;
        input pa_val;
        input pb_val;
        begin
            P_A = pa_val;
            P_B = pb_val;
            
            @(posedge clk);
            
            if (pa_val) N_PA = N_PA + 1;
            if (pb_val) N_PB = N_PB + 1;
            
            cycle_count = cycle_count + 1;
            
            #2;
            
            expected_value = (2 * N_PA + N_PB) % 4;
            
            $display("|   %0d   |  %0d  |  %0d  |    %0d   |    %0d   |        %0d        |  %0d   | %0d |    %0d    |", cycle_count, P_A, P_B, N_PA, N_PB, 2*N_PA + N_PB, expected_value, O, (expected_value == 1));
            
        end
    endtask

endmodule

Assignment_4/vcd/assign4_problem4_state_diagram_implementation.vcd
$date
	Mon Sep 15 22:35:41 2025
$end
$version
	Icarus Verilog
$end
$timescale
	1s
$end
$scope module state_diagram_implementation_tb $end
$var wire 1 ! O $end
$var integer 32 " N_PA [31:0] $end
$var integer 32 # N_PB [31:0] $end
$var reg 1 $ P_A $end
$var reg 1 % P_B $end
$var reg 1 & clk $end
$var integer 32 ' cycle_count [31:0] $end
$var integer 32 ( expected_value [31:0] $end
$var reg 192 ) name [191:0] $end
$var reg 1 * reset $end
$upscope $end
$enddefinitions $end
#0
$dumpvars
1*
b10010110111010101101110011101110110000101110010001000000100000101110010011100000110100101110100001000000101001101101001011011100110011101101000001000000011001000110010001100010011100000110101 )
bx (
b0 '
0&
0%
0$
b0 #
b0 "
0!
$end
#5
1&
#10
0&
0*
#15
b1 '
1&
#17
1%
1$
b0 (
#20
0&
#25
b10 '
b1 #
b1 "
1&
#27
0%
b11 (
#30
0&
#35
1!
b11 '
b10 "
1&
#37
1%
0$
b1 (
#40
0&
#45
0!
b100 '
b10 #
1&
#47
1$
b10 (
#50
0&
#55
1!
b101 '
b11 #
b11 "
1&
#57
0%
0$
b1 (
#60
0&
#65
b110 '
1&
#67
1$
#70
0&
#75
0!
b111 '
b100 "
1&
#77
1%
0$
b11 (
#80
0&
#85
b1000 '
b100 #
1&
#87
b0 (
#90
0&
#95
1!
1&
#100
0&
#105
0!
1&
