Assignment_4/.v files/assign4_problem1_moore_machine.v
module moore_machine (input CLK, input RESET, input A, input B, output reg Q);

    parameter S0 = 2'b00;
    parameter S1 = 2'b01;
    parameter S2 = 2'b10;
    
    reg [1:0] current_state;
    reg [1:0] next_state;

    always @(posedge CLK) begin
        if (RESET) begin
            current_state <= S0;
        end else begin
            current_state <= next_state;
        end
    end

    always @(*) begin
        case (current_state)
            S0: begin
                if (A)
                    next_state = S1;
                else
                    next_state = S0;
            end

            S1: begin
                if (B)
                    next_state = S2;
                else
                    next_state = S0;
            end

            S2: begin
                next_state = S0;
            end
            
            default: begin
                next_state = S0;
            end
        endcase
    end

    always @(*) begin
        case (current_state)
            S0: Q = 1'b0;
            S1: Q = 1'b0;
            S2: Q = 1'b1;
            default: Q = 1'b0;
        endcase
    end
endmodule

Assignment_4/Testbench/assign4_problem1_moore_machine_tb.v
module moore_machine_tb;

    reg clk;
    reg reset;
    reg A;
    reg B;
    wire Q;
    reg [8*24-1:0] name;

    moore_machine dut (.CLK(clk), .RESET(reset), .A(A), .B(B), .Q(Q));

    initial begin
        clk = 0;
        forever #5 clk = ~clk;
    end

    initial begin
        name = " Kunwar Arpit Singh 22185";
        $display("Kunwar Arpit Singh");
        $dumpfile("assign4_problem1_moore_machine.vcd");
        $dumpvars(1, moore_machine_tb);
        $display("Kunwar Arpit Singh");

        $display("| CLK | RESET | A | B | State | Output Q  |");
        $monitor("|  %b  |   %b   | %b | %b |   %b   |     %b     |", clk, reset, A, B, dut.current_state, Q);

        reset = 1; A = 0; B = 0;
        @(posedge clk);
        @(posedge clk);

        reset = 0;
        @(posedge clk);

        A = 0; B = 1;
        $display("For S0 -> S0 (A=0)");
        $display("| CLK | RESET | A | B |  State | Output Q  |");
        @(posedge clk);

        A = 1; B = 0;
        $display("For S0 -> S1 (A=1)");
        $display("| CLK | RESET | A | B |  State | Output Q  |");
        @(posedge clk);

        A = 1; B = 0;
        $display("For S1 -> S0 (B=0)");
        $display("| CLK | RESET | A | B |  State | Output Q  |");
        @(posedge clk);

        A = 1; B = 0;
        $display("For transition to S1");
        $display("| CLK | RESET | A | B |  State | Output Q  |");
        @(posedge clk);

        A = 0; B = 1;
        $display("For S1 -> S2 (B=1)");
        $display("| CLK | RESET | A | B |  State | Output Q  |");
        @(posedge clk);

        A = 1; B = 1;
        $display("For S2 -> S0 (unconditional)");
        $display("| CLK | RESET | A | B |  State | Output Q  |"); 
        @(posedge clk);

        @(posedge clk);
        @(posedge clk);
        $finish;
    end
endmodule

Assignment_4/vcd/assign4_problem1_moore_machine.vcd
$date
	Mon Sep 15 15:44:07 2025
$end
$version
	Icarus Verilog
$end
$timescale
	1s
$end
$scope module moore_machine_tb $end
$var wire 1 ! Q $end
$var reg 1 " A $end
$var reg 1 # B $end
$var reg 1 $ clk $end
$var reg 192 % name [191:0] $end
$var reg 1 & reset $end
$upscope $end
$enddefinitions $end
#0
$dumpvars
1&
b10010110111010101101110011101110110000101110010001000000100000101110010011100000110100101110100001000000101001101101001011011100110011101101000001000000011001000110010001100010011100000110101 %
0$
0#
0"
x!
$end
#5
0!
1$
#10
0$
#15
0&
1$
#20
0$
#25
1#
1$
#30
0$
#35
0#
1"
1$
#40
0$
#45
1$
#50
0$
#55
1$
#60
0$
#65
1#
0"
1$
#70
0$
#75
1!
1"
1$
#80
0$
#85
0!
1$
#90
0$
#95
1$
#100
0$
#105
1!
1$
