Assignment_4/.v files/assign4_problem3_FSM_implementation.v
module fsm_implementation(input CLK, input RESET, input x, output reg Z);

    parameter S0 = 2'b00;
    parameter S1 = 2'b01;
    parameter S2 = 2'b10;
    parameter S3 = 2'b11;
    
    reg [1:0] current_state;
    reg [1:0] next_state;

    always @(posedge CLK or posedge RESET) begin
        if(RESET)
            current_state <= S0;
        else
            current_state <= next_state;
    end

    always @(current_state or x) begin
        case (current_state)
            S0:
                if(x)
                    next_state = S1;
                else
                    next_state = S0;
            S1:
                if(x)
                    next_state = S2;
                else
                    next_state = S0;
            S2:
                if(x)
                    next_state = S2;
                else
                    next_state = S3;
            S3:
                if(x)
                    next_state = S1;
                else
                    next_state = S0;
            default:
                next_state = S0;
        endcase
    end

    always @(current_state or x) begin
        if (current_state == S3 && x == 1'b1)
            Z = 1'b1;
        else
            Z = 1'b0;
    end

endmodule

Assignment_4/Testbench/assign4_problem3_FSM_implementation_tb.v
module fsm_implementation_tb;
    reg clk;
    reg reset;
    reg x;
    wire Z;
    reg [8*24-1:0] name;

    fsm_implementation dut (.CLK(clk), .RESET(reset), .x(x), .Z(Z));

    initial begin
        clk = 0;
        forever #5 clk = ~clk;
    end

    initial begin
        name = " Kunwar Arpit Singh 22185";
        $display("Kunwar Arpit Singh");
        $dumpfile("assign4_problem3_FSM_implementation.vcd");
        $dumpvars(1, fsm_implementation_tb);
        $display("Kunwar Arpit Singh");
        
        reset = 1;
        x = 0;
        @(negedge clk);
        @(negedge clk);
        reset = 0;

        $display("\nFor Sequence: 1101");
        $display("| Reset | Input x | State | Output Z |");
        @(negedge clk) x = 1;
        @(negedge clk) x = 1;
        @(negedge clk) x = 0;
        @(negedge clk) x = 1;
        @(negedge clk) x = 0;

        $display("\nFor Sequence: 011010");
        $display("| Reset | Input x | State | Output Z |");
        @(negedge clk) x = 0;
        @(negedge clk) x = 1;
        @(negedge clk) x = 1;
        @(negedge clk) x = 0;
        @(negedge clk) x = 1;
        @(negedge clk) x = 0;

        $display("\nFor Sequence: 1101101");
        $display("| Reset | Input x | State | Output Z |");
        @(negedge clk) x = 1;
        @(negedge clk) x = 1;
        @(negedge clk) x = 0;
        @(negedge clk) x = 1;
        @(negedge clk) x = 1;
        @(negedge clk) x = 0;
        @(negedge clk) x = 1;
        @(negedge clk) x = 0;

        $display("\nFor Sequence: 11101");
        $display("| Reset | Input x | State | Output Z |");
        @(negedge clk) x = 1;
        @(negedge clk) x = 1;
        @(negedge clk) x = 1;
        @(negedge clk) x = 0;
        @(negedge clk) x = 1;
        @(negedge clk) x = 0;

        $display("\nFor Sequence: 0010100");
        $display("| Reset | Input x | State | Output Z |");
        @(negedge clk) x = 0;
        @(negedge clk) x = 0;
        @(negedge clk) x = 1;
        @(negedge clk) x = 0;
        @(negedge clk) x = 1;
        @(negedge clk) x = 0;
        @(negedge clk) x = 0;
        
        #20 $finish;
    end

    // Monitor with timestamps for clearer debugging
    initial begin
        $monitor("|   %b   |    %b    |   %b  |     %b    |", reset, x, dut.current_state, Z);
    end

endmodule

Assignment_4/vcd/assign4_problem3_FSM_implementation.vcd
$date
	Mon Sep 15 19:54:39 2025
$end
$version
	Icarus Verilog
$end
$timescale
	1s
$end
$scope module fsm_implementation_tb $end
$var wire 1 ! Z $end
$var reg 1 " clk $end
$var reg 192 # name [191:0] $end
$var reg 1 $ reset $end
$var reg 1 % x $end
$upscope $end
$enddefinitions $end
#0
$dumpvars
0%
1$
b10010110111010101101110011101110110000101110010001000000100000101110010011100000110100101110100001000000101001101101001011011100110011101101000001000000011001000110010001100010011100000110101 #
0"
0!
$end
#5
1"
#10
0"
#15
1"
#20
0$
0"
#25
1"
#30
1%
0"
#35
1"
#40
0"
#45
1"
#50
0%
0"
#55
1"
#60
1!
1%
0"
#65
0!
1"
#70
0%
0"
#75
1"
#80
0"
#85
1"
#90
1%
0"
#95
1"
#100
0"
#105
1"
#110
0%
0"
#115
1"
#120
1!
1%
0"
#125
0!
1"
#130
0%
0"
#135
1"
#140
1%
0"
#145
1"
#150
0"
#155
1"
#160
0%
0"
#165
1"
#170
1!
1%
0"
#175
0!
1"
#180
0"
#185
1"
#190
0%
0"
#195
1"
#200
1!
1%
0"
#205
0!
1"
#210
0%
0"
#215
1"
#220
1%
0"
#225
1"
#230
0"
#235
1"
#240
0"
#245
1"
#250
0%
0"
#255
1"
#260
1!
1%
0"
#265
0!
1"
#270
0%
0"
#275
1"
#280
0"
#285
1"
#290
0"
#295
1"
#300
1%
0"
#305
1"
#310
0%
0"
#315
1"
#320
1%
0"
#325
1"
#330
0%
0"
