Assignment_4/.v files/assign4_problem2_mealy_machine.v
module mealy_machine(input CLK, input RESET, input A, input B, output reg Y);

    parameter S0 = 2'b00;
    parameter S1 = 2'b01;
    parameter S2 = 2'b10;

    reg [1:0] current_state; 
    reg [1:0] next_state;

    always @(posedge CLK) begin
        if (RESET)
            current_state <= S0;
        else
            current_state <= next_state;
    end

    always @(current_state or A or B) begin
        case (current_state)
            S0: begin
                if (A)
                    next_state = S1;
                else
                    next_state = S0;
            end
            S1: begin
                if (B)
                    next_state = S2;
                else
                    next_state = S0;
            end
            S2: begin
                if (A && B)
                    next_state = S2;
                else
                    next_state = S0;
            end
            default: begin
                next_state = S0;
            end
        endcase
    end

    always @(current_state or A or B) begin
        case (current_state)
            S0: Y = 0;
            S1: Y = 0;
            S2: begin
                if (A && B)
                    Y = 1;
                else
                    Y = 0;
            end
            default: Y = 0;
        endcase
    end

endmodule

Assignment_4/Testbench/assign4_problem2_mealy_machine_tb.v
module mealy_machine_tb;

    reg clk;
    reg reset;
    reg A;
    reg B;
    wire Y;
    reg [8*24-1:0] name;
    mealy_machine dut (.CLK(clk), .RESET(reset), .A(A), .B(B), .Y(Y));

    initial begin
        clk = 0;
        forever #5 clk = ~clk;
    end

    initial begin
        name = " Kunwar Arpit Singh 22185";
        $display("Kunwar Arpit Singh");
        $dumpfile("assign4_problem2_mealy_machine.vcd");
        $dumpvars(1, mealy_machine_tb);
        $display("Kunwar Arpit Singh");
        $display("| Reset | A | B |  State |  Output Y |");
        $monitor("|   %b   | %b | %b |   %b   |     %b     |", reset, A, B, dut.current_state, Y);

        reset = 1; A = 0; B = 0;
        #15;

        reset = 0;
        #10;

        A = 0; B = 0; #10;
        A = 1; B = 0; #10;

        A = 1; B = 0; #10;
        A = 1; B = 0; #10;
        A = 0; B = 1; #10;

        A = 1; B = 1; #10;
        A = 1; B = 1; #10;

        A = 0; B = 1; #10;

        A = 1; B = 0; #10;
        A = 0; B = 1; #10;

        A = 1; B = 0; #10;

        #20;
        $finish;
    end

endmodule

Assignment_4/vcd/assign4_problem2_mealy_machine.vcd
$date
	Mon Sep 15 17:55:03 2025
$end
$version
	Icarus Verilog
$end
$timescale
	1s
$end
$scope module mealy_machine_tb $end
$var wire 1 ! Y $end
$var reg 1 " A $end
$var reg 1 # B $end
$var reg 1 $ clk $end
$var reg 192 % name [191:0] $end
$var reg 1 & reset $end
$upscope $end
$enddefinitions $end
#0
$dumpvars
1&
b10010110111010101101110011101110110000101110010001000000100000101110010011100000110100101110100001000000101001101101001011011100110011101101000001000000011001000110010001100010011100000110101 %
0$
0#
0"
0!
$end
#5
1$
#10
0$
#15
1$
0&
#20
0$
#25
1$
#30
0$
#35
1$
1"
#40
0$
#45
1$
#50
0$
#55
1$
#60
0$
#65
1$
1#
0"
#70
0$
#75
1!
1$
1"
#80
0$
#85
1$
#90
0$
#95
0!
1$
0"
#100
0$
#105
1$
0#
1"
#110
0$
#115
1$
1#
0"
#120
0$
#125
1$
0#
1"
