Assignment_3/.v files/assign3_problem4_gray_code_counter.v
module gray_counter(input CLK, input RESET, input UP, output reg [2:0] GRAYout);

    always @(posedge CLK or posedge RESET) begin
        if (RESET) begin
            GRAYout <= 3'b000;
        end else begin
            if (UP) begin
                case (GRAYout)
                    3'b000: GRAYout <= 3'b001;
                    3'b001: GRAYout <= 3'b011;
                    3'b011: GRAYout <= 3'b010;
                    3'b010: GRAYout <= 3'b110;
                    3'b110: GRAYout <= 3'b111;
                    3'b111: GRAYout <= 3'b101;
                    3'b101: GRAYout <= 3'b100;
                    3'b100: GRAYout <= 3'b000;
                    default: GRAYout <= 3'b000;
                endcase
            end
        end
    end
endmodule

Assignment_3/Testbench/assign3_problem4_gray_code_counter_tb.v
module gray_counter_tb;
    reg CLK;
    reg RESET;
    reg UP;
    wire [2:0] GRAYout;
    reg [8*24-1:0] name;
    gray_counter dut (.CLK(CLK), .RESET(RESET), .UP(UP), .GRAYout(GRAYout));

    initial begin
        CLK = 0;
        forever #5 CLK = ~CLK;
    end

    initial begin
        name = " Kunwar Arpit Singh 22185";
        $dumpfile("assign3_problem4_gray_code_counter.vcd");
        $dumpvars(1, gray_counter_tb);

        $display("Kunwar Arpit Singh");
        $display("| Reset | UP | Gray Output |");
        $display("----------------------------");
        $monitor("|   %b   |  %b |    %b (%d)   |", RESET, UP, GRAYout, GRAYout);

        RESET = 1; UP = 0; #20;
        RESET = 0; #5;
        
        UP = 1; #70;

        UP = 0; #40;

        UP = 1; #30;
        $finish;
    end
endmodule

Assignment_3/vcd/assign3_problem4_gray_code_counter.vcd
$date
	Sun Sep 14 19:44:00 2025
$end
$version
	Icarus Verilog
$end
$timescale
	1s
$end
$scope module gray_counter_tb $end
$var wire 3 ! GRAYout [2:0] $end
$var reg 1 " CLK $end
$var reg 1 # RESET $end
$var reg 1 $ UP $end
$var reg 192 % name [191:0] $end
$upscope $end
$enddefinitions $end
#0
$dumpvars
b10010110111010101101110011101110110000101110010001000000100000101110010011100000110100101110100001000000101001101101001011011100110011101101000001000000011001000110010001100010011100000110101 %
0$
1#
0"
b0 !
$end
#5
1"
#10
0"
#15
1"
#20
0"
0#
#25
b1 !
1"
1$
#30
0"
#35
b11 !
1"
#40
0"
#45
b10 !
1"
#50
0"
#55
b110 !
1"
#60
0"
#65
b111 !
1"
#70
0"
#75
b101 !
1"
#80
0"
#85
b100 !
1"
#90
0"
#95
1"
0$
#100
0"
#105
1"
#110
0"
#115
1"
#120
0"
#125
1"
#130
0"
#135
b0 !
1"
1$
#140
0"
#145
b1 !
1"
#150
0"
#155
b11 !
1"
#160
0"
#165
b10 !
1"
