Assignment_3/.v files/assign3_problem5_bidirectional_shift_register.v
module shift_register #(parameter N = 8)(input clk, reset, input shift_en, load_en, input direction, input serial_in, input [N-1:0] parallel_in, output reg [N-1:0] parallel_out);

    always @(posedge clk, posedge reset) begin
        if (reset) begin
            parallel_out <= {N{1'b0}};
        end else if (load_en) begin
            parallel_out <= parallel_in;
        end else if (shift_en) begin
            if (direction) begin
                parallel_out <= {serial_in, parallel_out[N-1:1]};
            end else begin
                parallel_out <= {parallel_out[N-2:0], serial_in};
            end
        end
    end

endmodule

Assignment_3/Testbench/assign3_problem5_bidirectional_shift_register_tb.v
module shift_register_tb;
    localparam N = 8;
    reg clk;
    reg reset;
    reg shift_en, load_en, direction, serial_in;
    reg [N-1:0] parallel_in;
    wire [N-1:0] parallel_out;
    reg [8*24-1:0] name;
    shift_register #(.N(N)) dut (.clk(clk), .reset(reset), .shift_en(shift_en), .load_en(load_en), .direction(direction), .serial_in(serial_in), .parallel_in(parallel_in), .parallel_out(parallel_out)
    );

    initial begin
        clk = 0;
        forever #5 clk = ~clk;
    end

    initial begin
        name = " Kunwar Arpit Singh 22185";
        $dumpfile("assign3_problem5_bidirectional_shift_register.vcd");
        $dumpvars(1, shift_register_tb);
        $display("--- N-Bit Shift Register Simulation (N=%0d) ---", N);
        $display("Kunwar Arpit Singh");
        $display("| Reset | Load_en | Shift_en | Direction | Serial_in | Parallel_out |");
        reset = 1; #20; reset = 0;
        $monitor("%b | %b | %b | %b | %b | %b", reset, load_en, shift_en, direction, serial_in, parallel_out);

        load_en = 1; parallel_in = 8'b10110101;
        #10;
        load_en = 0;
        #10;

        shift_en = 1; direction = 1;
        serial_in = 1;
        #10;
        serial_in = 0;
        #10;
        serial_in = 1;
        #10;

        direction = 0;
        serial_in = 0;
        #10;
        serial_in = 1;
        #10;
        serial_in = 0;
        #10;
        shift_en = 0;
        
        $finish;
    end
endmodule

Assignment_3/vcd/assign3_problem5_bidirectional_shift_register.vcd
$date
	Sun Sep 14 20:20:32 2025
$end
$version
	Icarus Verilog
$end
$timescale
	1s
$end
$scope module shift_register_tb $end
$var wire 8 ! parallel_out [7:0] $end
$var reg 1 " clk $end
$var reg 1 # direction $end
$var reg 1 $ load_en $end
$var reg 192 % name [191:0] $end
$var reg 8 & parallel_in [7:0] $end
$var reg 1 ' reset $end
$var reg 1 ( serial_in $end
$var reg 1 ) shift_en $end
$upscope $end
$enddefinitions $end
#0
$dumpvars
x)
x(
1'
bx &
b10010110111010101101110011101110110000101110010001000000100000101110010011100000110100101110100001000000101001101101001011011100110011101101000001000000011001000110010001100010011100000110101 %
x$
x#
0"
b0 !
$end
#5
1"
#10
0"
#15
1"
#20
0"
b10110101 &
1$
0'
#25
b10110101 !
1"
#30
0"
0$
#35
1"
#40
0"
1(
1#
1)
#45
b11011010 !
1"
#50
0"
0(
#55
b1101101 !
1"
#60
0"
1(
#65
b10110110 !
1"
#70
0"
0(
0#
#75
b1101100 !
1"
#80
0"
1(
#85
b11011001 !
1"
#90
0"
0(
#95
b10110010 !
1"
#100
0"
0)
