Assignment_3/.v files/assign3_problem6_single_port_RAM.v
module simple_dual_port_ram #(parameter DATA_WIDTH = 16, parameter ADDR_WIDTH = 7)( input clk, input we, input [ADDR_WIDTH-1:0] waddr, input [ADDR_WIDTH-1:0] raddr, input [DATA_WIDTH-1:0] wdata, output reg [DATA_WIDTH-1:0] rdata);

    localparam DEPTH = 1 << ADDR_WIDTH;

    reg [DATA_WIDTH-1:0] memory [0:DEPTH-1];

    always @(posedge clk) begin
        if (we) begin
            memory[waddr] <= wdata;
        end
        rdata <= memory[raddr];
    end

endmodule

Assignment_3/Testbench/assign3_problem6_single_port_RAM_tb.v
module simple_dual_port_ram_tb;

    localparam DATA_WIDTH = 16;
    localparam ADDR_WIDTH = 7;

    reg clk;
    reg we;
    reg [ADDR_WIDTH-1:0] waddr;
    reg [ADDR_WIDTH-1:0] raddr;
    reg [DATA_WIDTH-1:0] wdata;
    wire [DATA_WIDTH-1:0] rdata;
    reg [8*24-1:0] name;
    simple_dual_port_ram #(.DATA_WIDTH(DATA_WIDTH), .ADDR_WIDTH(ADDR_WIDTH)) dut (.clk(clk), .we(we), .waddr(waddr), .raddr(raddr), .wdata(wdata), .rdata(rdata));

    initial begin
        clk = 0;
        forever #5 clk = ~clk;    end

    initial begin
        name = " Kunwar Arpit Singh 22185";
        $dumpfile("assign3_problem6_single_port_RAM.vcd");
        $dumpvars(1, simple_dual_port_ram_tb);
        $display("Kunwar Arpit Singh");
        $display("| WE | WAddr | WData | RAddr | RData");
        $monitor("| %b | %d | %h | %d | %h", we, waddr, wdata, raddr, rdata);

        we = 0;
        waddr = 0;
        raddr = 0;
        wdata = 0;
        #10;

        we = 1;
        waddr = 10;
        wdata = 16'hABCD;
        #10;
        we = 0;
        #10;

        we = 1;
        waddr = 42;
        wdata = 16'hDEAD;
        #10;
        we = 0;
        #10;

        raddr = 10;
        #10;
        raddr = 42;
        #10;
        raddr = 5;
        #10;
        we = 1;
        waddr = 127;
        wdata = 16'hFD;
        raddr = 10;
        #10;
        we = 0;
        #10;

        raddr = 127;
        #10;

        $finish;
    end

endmodule

Assignment_3/vcd/assign3_problem6_single_port_RAM.vcd
$date
	Sun Sep 14 20:20:38 2025
$end
$version
	Icarus Verilog
$end
$timescale
	1s
$end
$scope module simple_dual_port_ram_tb $end
$var wire 16 ! rdata [15:0] $end
$var reg 1 " clk $end
$var reg 192 # name [191:0] $end
$var reg 7 $ raddr [6:0] $end
$var reg 7 % waddr [6:0] $end
$var reg 16 & wdata [15:0] $end
$var reg 1 ' we $end
$upscope $end
$enddefinitions $end
#0
$dumpvars
0'
b0 &
b0 %
b0 $
b10010110111010101101110011101110110000101110010001000000100000101110010011100000110100101110100001000000101001101101001011011100110011101101000001000000011001000110010001100010011100000110101 #
0"
bx !
$end
#5
1"
#10
0"
b1010101111001101 &
b1010 %
1'
#15
1"
#20
0"
0'
#25
1"
#30
0"
b1101111010101101 &
b101010 %
1'
#35
1"
#40
0"
0'
#45
1"
#50
0"
b1010 $
#55
b1010101111001101 !
1"
#60
0"
b101010 $
#65
b1101111010101101 !
1"
#70
0"
b101 $
#75
bx !
1"
#80
0"
b1010 $
b11111101 &
b1111111 %
1'
#85
b1010101111001101 !
1"
#90
0"
0'
#95
1"
#100
0"
b1111111 $
#105
b11111101 !
1"
