Assignment_3/.v files/assign3_problem3_counter.v
module binary_counter(input CLK, input RESET, output reg [2:0] COUNT);

    always @(posedge CLK, posedge RESET) begin
        if (RESET) begin
            COUNT <= 3'b111;
        end 
        else begin
            if (COUNT == 3'b000) begin
                COUNT <= 3'b111;
            end else begin
                COUNT <= COUNT - 1;
            end
        end
    end
endmodule

Assignment_3/Testbench/assign3_problem3_counter_tb.v
module binary_counter_tb;
    reg CLK;
    reg RESET;
    wire [2:0] COUNT;
    reg [8*24-1:0] name;

    binary_counter dut (.CLK(CLK), .RESET(RESET), .COUNT(COUNT));

    initial begin
        CLK = 0;
        forever #5 CLK = ~CLK;
    end

    initial begin
        name = " Kunwar Arpit Singh 22185";
        
        $dumpfile("assign3_problem3_counter.vcd");
        $dumpvars(1, binary_counter_tb);

        $display("Kunwar Arpit Singh");
        $display("| Reset | Clock | Count |");
        $display("----------------------");

        $monitor("| %b | %b | %b (%d) |", RESET, CLK, COUNT, COUNT);
        RESET = 1; #15;
        RESET = 0; #65;
        $finish;
    end
endmodule

Assignment_3/vcd/assign3_problem3_counter.vcd
$date
	Sun Sep 14 19:09:36 2025
$end
$version
	Icarus Verilog
$end
$timescale
	1s
$end
$scope module binary_counter_tb $end
$var wire 3 ! COUNT [2:0] $end
$var reg 1 " CLK $end
$var reg 1 # RESET $end
$var reg 192 $ name [191:0] $end
$upscope $end
$enddefinitions $end
#0
$dumpvars
b10010110111010101101110011101110110000101110010001000000100000101110010011100000110100101110100001000000101001101101001011011100110011101101000001000000011001000110010001100010011100000110101 $
1#
0"
b111 !
$end
#5
1"
#10
0"
#15
b110 !
1"
0#
#20
0"
#25
b101 !
1"
#30
0"
#35
b100 !
1"
#40
0"
#45
b11 !
1"
#50
0"
#55
b10 !
1"
#60
0"
#65
b1 !
1"
#70
0"
#75
b0 !
1"
#80
0"
#85
b111 !
1"
