Assignment_3/.v files/assign3_problem1_sr_latch.v
module sr_latch(input S, input R, input en, input reset, output reg Q, output reg Q_n);
    always @(S, R, en, reset) begin
        if (reset) begin
            Q <=1'b0;
            Q_n <= 1'b1;
        end
        else if (en) begin
            case ({S, R})
                2'b00: begin
                    Q <= Q;
                    Q_n <= Q_n;
                end
                
                2'b01: begin
                    Q <= 1'b0;
                    Q_n <=1'b1;
                end

                2'b10: begin
                    Q <= 1'b1;
                    Q_n <=1'b0;
                end

                2'b11: begin
                    Q <= 1'bx;
                    Q_n <= 1'bx;
                end
            endcase
        end
    end
endmodule

Assignment_3/Testbench/assign3_problem1_sr_latch_tb.v
module sr_latch_tb;
    reg S;
    reg R;
    reg en;
    reg reset;
    wire Q;
    wire Q_n;
    reg [8*24-1:0] name;
    sr_latch dut (.S(S), .R(R), .en(en), .reset(reset), .Q(Q), .Q_n(Q_n));

    initial begin
        name = " Kunwar Arpit Singh 22185";
        $display("Kunwar Arpit Singh");
        $dumpfile("assign3_problem1_sr_latch.vcd");
        $dumpvars(1, sr_latch_tb);
        $display("Kunwar Arpit Singh");

        $display("| reset | en | S | R | Q |  Q_n |");
        $display("---------------------------------");

        reset = 1'b1; S = 1'b0; R = 1'b0; en = 1'b0; #10;
        $display("|   %b   | %b  | %b | %b | %b |  %b  |",reset, en, S, R, Q, Q_n);

        reset = 1'b0; S = 1'b0; R = 1'b0; en = 1'b0; #10;
        $display("|   %b   | %b  | %b | %b | %b |  %b  |",reset, en, S, R, Q, Q_n);

        reset = 1'b0; S = 1'b0; R = 1'b0; en = 1'b1; #10;
        $display("|   %b   | %b  | %b | %b | %b |  %b  |",reset, en, S, R, Q, Q_n);

        reset = 1'b0; S = 1'b0; R = 1'b1; en = 1'b1; #10;
        $display("|   %b   | %b  | %b | %b | %b |  %b  |",reset, en, S, R, Q, Q_n);

        reset = 1'b0; S = 1'b0; R = 1'b0; en = 1'b1; #10;
        $display("|   %b   | %b  | %b | %b | %b |  %b  |",reset, en, S, R, Q, Q_n);

        reset = 1'b0; S = 1'b1; R = 1'b0; en = 1'b1; #10;
        $display("|   %b   | %b  | %b | %b | %b |  %b  |",reset, en, S, R, Q, Q_n);
        
        reset = 1'b0; S = 1'b0; R = 1'b0; en = 1'b1; #10;
        $display("|   %b   | %b  | %b | %b | %b |  %b  |",reset, en, S, R, Q, Q_n);

        reset = 1'b0; S = 1'b1; R = 1'b1; en = 1'b1; #10;
        $display("|   %b   | %b  | %b | %b | %b |  %b  |",reset, en, S, R, Q, Q_n);

        $finish;
    end
endmodule

Assignment_3/vcd/assign3_problem1_sr_latch.vcd
$date
	Thu Sep 11 23:10:22 2025
$end
$version
	Icarus Verilog
$end
$timescale
	1s
$end
$scope module sr_latch_tb $end
$var wire 1 ! Q $end
$var wire 1 " Q_n $end
$var reg 1 # R $end
$var reg 1 $ S $end
$var reg 1 % en $end
$var reg 192 & name [191:0] $end
$var reg 1 ' reset $end
$upscope $end
$enddefinitions $end
#0
$dumpvars
1'
b10010110111010101101110011101110110000101110010001000000100000101110010011100000110100101110100001000000101001101101001011011100110011101101000001000000011001000110010001100010011100000110101 &
0%
0$
0#
1"
0!
$end
#10
0'
#20
1%
#30
1#
#40
0#
#50
0"
1!
1$
#60
0$
#70
x"
x!
1#
1$
