Assignment_2/.v files/assign2_problem2_encoder_4_to_2.v
module encoder_4_to_2 (input [3:0] A, output [1:0] out);
    assign out = (A == 4'b1000) ? 2'b11 :
                 (A == 4'b0100) ? 2'b10 :
                 (A == 4'b0010) ? 2'b01 :
                 (A == 4'b0001) ? 2'b00 : 2'bxx;
endmodule

Assignment_2/Testbench/assign2_problem2_encoder_4_to_2_tb.v
module encoder_4_to_2_tb;
    reg [3:0] A;
    wire [1:0] out;
    reg [8*24-1:0] name;

    encoder_4_to_2 dut (.A(A), .out(out));

    initial begin
        name = " Kunwar Arpit Singh 22185";
        $dumpfile("assign2_problem2_encoder_4_to_2.vcd");
        $dumpvars(1, encoder_4_to_2_tb);
        $display("Kunwar Arpit Singh");
        $display("Output for only the valid cases for 4 to 2 encoder");
        $display("A (Binary & Decimal) | Output(Binary) | Output(Decimal)");
        $display("----------------------------------------------");
        A = 4'b0001; #10;
        $display("%b    |   %d  |   %b  |   %d", A, A, out, out);
        A = 4'b0010; #10;
        $display("%b    |   %d  |   %b  |   %d", A, A, out, out);
        A = 4'b0100; #10;
        $display("%b    |   %d  |   %b  |   %d", A, A, out, out);
        A = 4'b1000; #10;
        $display("%b    |   %d  |   %b  |   %d", A, A, out, out);
        $display("\nOutput for all the cases for 4 to 2 encoder");
        $display("A (Binary & Decimal) | Output(Binary) | Output(Decimal)");
        $display("----------------------------------------------");
        A = 4'b0000; #10;
        $display("%b    |   %d  |   %b  |   %d", A, A, out, out);
        A = 4'b0001; #10;
        $display("%b    |   %d  |   %b  |   %d", A, A, out, out);
        A = 4'b0010; #10;
        $display("%b    |   %d  |   %b  |   %d", A, A, out, out);
        A = 4'b0011; #10;
        $display("%b    |   %d  |   %b  |   %d", A, A, out, out);
        A = 4'b0100; #10;
        $display("%b    |   %d  |   %b  |   %d", A, A, out, out);
        A = 4'b0101; #10;
        $display("%b    |   %d  |   %b  |   %d", A, A, out, out);
        A = 4'b0110; #10;
        $display("%b    |   %d  |   %b  |   %d", A, A, out, out);
        A = 4'b0111; #10;
        $display("%b    |   %d  |   %b  |   %d", A, A, out, out);
        A = 4'b1000; #10;
        $display("%b    |   %d  |   %b  |   %d", A, A, out, out);
        A = 4'b1001; #10;
        $display("%b    |   %d  |   %b  |   %d", A, A, out, out);
        A = 4'b1010; #10;
        $display("%b    |   %d  |   %b  |   %d", A, A, out, out);
        A = 4'b1011; #10;
        $display("%b    |   %d  |   %b  |   %d", A, A, out, out);
        A = 4'b1100; #10;
        $display("%b    |   %d  |   %b  |   %d", A, A, out, out);
        A = 4'b1101; #10;
        $display("%b    |   %d  |   %b  |   %d", A, A, out, out);
        A = 4'b1110; #10;
        $display("%b    |   %d  |   %b  |   %d", A, A, out, out);
        A = 4'b1111; #10;
        $display("%b    |   %d  |   %b  |   %d", A, A, out, out);
        $finish;
    end
endmodule

Assignment_2/vcd/assign2_problem2_encoder_4_to_2.vcd
$date
	Wed Sep 10 00:30:20 2025
$end
$version
	Icarus Verilog
$end
$timescale
	1s
$end
$scope module encoder_4_to_2_tb $end
$var wire 2 ! out [1:0] $end
$var reg 4 " A [3:0] $end
$var reg 192 # name [191:0] $end
$upscope $end
$enddefinitions $end
#0
$dumpvars
b10010110111010101101110011101110110000101110010001000000100000101110010011100000110100101110100001000000101001101101001011011100110011101101000001000000011001000110010001100010011100000110101 #
b1 "
b0 !
$end
#10
b1 !
b10 "
#20
b10 !
b100 "
#30
b11 !
b1000 "
#40
bx !
b0 "
#50
b0 !
b1 "
#60
b1 !
b10 "
#70
bx !
b11 "
#80
b10 !
b100 "
#90
bx !
b101 "
#100
b110 "
#110
b111 "
#120
b11 !
b1000 "
#130
bx !
b1001 "
#140
b1010 "
#150
b1011 "
#160
b1100 "
#170
b1101 "
#180
b1110 "
#190
b1111 "
