Assignment_2/.v files/assign2_problem1_4_bit_multiply_by_2.v
module multiply_4_bit_by_2 (input [3:0] A, output [4:0] out);
  assign out = A << 1;
endmodule

Assignment_2/Testbench/assign2_problem1_4_bit_multiply_by_2_tb.v
module multiply_4_bit_by_2_tb;
    reg [3:0] A;
    wire [4:0] out;
    reg [8*24-1:0] name;

    multiply_4_bit_by_2 dut (.A(A), .out(out));

    initial begin
        $display("Kunwar Arpit Singh");
        name = " Kunwar Arpit Singh 22185";
        $dumpfile("assign2_problem1_4_bit_multiply_by_2.vcd");
        $dumpvars(1, multiply_4_bit_by_2_tb);
        $display("Kunwar Arpit Singh");

        $display("A (Binary & Decimal) | Output(Binary) | Output(Decimal)");
        $display("----------------------------------------------");

        A = 4'b0000; #10;
        $display("%b    |   %d  |   %b  |   %d", A, A, out, out);
        A = 4'b0001; #10;
        $display("%b    |   %d  |   %b  |   %d", A, A, out, out);
        A = 4'b0010; #10;
        $display("%b    |   %d  |   %b  |   %d", A, A, out, out);
        A = 4'b0011; #10;
        $display("%b    |   %d  |   %b  |   %d", A, A, out, out);
        A = 4'b0100; #10;
        $display("%b    |   %d  |   %b  |   %d", A, A, out, out);
        A = 4'b0101; #10;
        $display("%b    |   %d  |   %b  |   %d", A, A, out, out);
        A = 4'b0110; #10;
        $display("%b    |   %d  |   %b  |   %d", A, A, out, out);
        A = 4'b0111; #10;
        $display("%b    |   %d  |   %b  |   %d", A, A, out, out);
        A = 4'b1000; #10;
        $display("%b    |   %d  |   %b  |   %d", A, A, out, out);
        A = 4'b1001; #10;
        $display("%b    |   %d  |   %b  |   %d", A, A, out, out);
        A = 4'b1010; #10;
        $display("%b    |   %d  |   %b  |   %d", A, A, out, out);
        A = 4'b1011; #10;
        $display("%b    |   %d  |   %b  |   %d", A, A, out, out);
        A = 4'b1100; #10;
        $display("%b    |   %d  |   %b  |   %d", A, A, out, out);
        A = 4'b1101; #10;
        $display("%b    |   %d  |   %b  |   %d", A, A, out, out);
        A = 4'b1110; #10;
        $display("%b    |   %d  |   %b  |   %d", A, A, out, out);
        A = 4'b1111; #10;
        $display("%b    |   %d  |   %b  |   %d", A, A, out, out);
        $finish;
    end
endmodule

Assignment_2/vcd/assign2_problem1_4_bit_multiply_by_2.vcd
$date
	Tue Sep 09 22:47:53 2025
$end
$version
	Icarus Verilog
$end
$timescale
	1s
$end
$scope module multiply_4_bit_by_2_tb $end
$var wire 5 ! out [4:0] $end
$var reg 4 " A [3:0] $end
$var reg 192 # name [191:0] $end
$upscope $end
$enddefinitions $end
#0
$dumpvars
b10010110111010101101110011101110110000101110010001000000100000101110010011100000110100101110100001000000101001101101001011011100110011101101000001000000011001000110010001100010011100000110101 #
b0 "
b0 !
$end
#10
b10 !
b1 "
#20
b100 !
b10 "
#30
b110 !
b11 "
#40
b1000 !
b100 "
#50
b1010 !
b101 "
#60
b1100 !
b110 "
#70
b1110 !
b111 "
#80
b10000 !
b1000 "
#90
b10010 !
b1001 "
#100
b10100 !
b1010 "
#110
b10110 !
b1011 "
#120
b11000 !
b1100 "
#130
b11010 !
b1101 "
#140
b11100 !
b1110 "
#150
b11110 !
b1111 "
