Assignment_2/.v files/assign2_problem3_mutliplexer_8_to_1.v
module multiplexer_8_to_1(input [7:0] A, input [2:0] sel, output out);
    assign out = (sel == 3'b000) ? A[0] :
                 (sel == 3'b001) ? A[1] :
                 (sel == 3'b010) ? A[2] :
                 (sel == 3'b011) ? A[3] :
                 (sel == 3'b100) ? A[4] :
                 (sel == 3'b101) ? A[5] :
                 (sel == 3'b110) ? A[6] :
                 (sel == 3'b111) ? A[7] : 
                 1'bx;
endmodule

Assignment_2/Testbench/assign2_problem3_mutliplexer_8_to_1_tb.v
module multiplexer_8_to_1_tb;
    reg [7:0] A;
    reg [2:0] sel;
    wire out;
    reg [8*24-1:0] name;

    multiplexer_8_to_1 uut (.A(A), .sel(sel), .out(out));

    initial begin
        name = " Kunwar Arpit Singh 22185";
        $display("Kunwar Arpit Singh");
        $dumpfile("assign2_problem3_mutliplexer_8_to_1.vcd");
        $dumpvars(1, multiplexer_8_to_1_tb);
        $display("Kunwar Arpit Singh");
        A = 8'b11001010;
        $display("Output for all the cases");
        $display("A (Binary & Decimal) | Output(Binary) | Output(Decimal)");
        $display("------------------------");
        sel = 3'b000; #10;
        $display("%b  |  %d  |  %b  |  %d  |  %b  |  %d  ", A, A, sel, sel, out, out);
        sel = 3'b001; #10;
        $display("%b  |  %d  |  %b  |  %d  |  %b  |  %d  ", A, A, sel, sel, out, out);
        sel = 3'b010; #10;
        $display("%b  |  %d  |  %b  |  %d  |  %b  |  %d  ", A, A, sel, sel, out, out);
        sel = 3'b011; #10;
        $display("%b  |  %d  |  %b  |  %d  |  %b  |  %d  ", A, A, sel, sel, out, out);
        sel = 3'b100; #10;
        $display("%b  |  %d  |  %b  |  %d  |  %b  |  %d  ", A, A, sel, sel, out, out);
        sel = 3'b101; #10;
        $display("%b  |  %d  |  %b  |  %d  |  %b  |  %d  ", A, A, sel, sel, out, out);
        sel = 3'b110; #10;
        $display("%b  |  %d  |  %b  |  %d  |  %b  |  %d  ", A, A, sel, sel, out, out);
        sel = 3'b111; #10;
        $display("%b  |  %d  |  %b  |  %d  |  %b  |  %d  ", A, A, sel, sel, out, out);

        A = 8'b00110101;
        $display("Output for all the cases");
        $display("A (Binary & Decimal) | Output(Binary) | Output(Decimal)");
        $display("------------------------");
        sel = 3'b000; #10;
        $display("%b  |  %d  |  %b  |  %d  |  %b  |  %d  ", A, A, sel, sel, out, out);
        sel = 3'b001; #10;
        $display("%b  |  %d  |  %b  |  %d  |  %b  |  %d  ", A, A, sel, sel, out, out);
        sel = 3'b010; #10;
        $display("%b  |  %d  |  %b  |  %d  |  %b  |  %d  ", A, A, sel, sel, out, out);
        sel = 3'b011; #10;
        $display("%b  |  %d  |  %b  |  %d  |  %b  |  %d  ", A, A, sel, sel, out, out);
        sel = 3'b100; #10;
        $display("%b  |  %d  |  %b  |  %d  |  %b  |  %d  ", A, A, sel, sel, out, out);
        sel = 3'b101; #10;
        $display("%b  |  %d  |  %b  |  %d  |  %b  |  %d  ", A, A, sel, sel, out, out);
        sel = 3'b110; #10;
        $display("%b  |  %d  |  %b  |  %d  |  %b  |  %d  ", A, A, sel, sel, out, out);
        sel = 3'b111; #10;
        $display("%b  |  %d  |  %b  |  %d  |  %b  |  %d  ", A, A, sel, sel, out, out);
        $finish;
    end
endmodule

Assignment_2/vcd/assign2_problem3_mutliplexer_8_to_1.vcd
$date
	Wed Sep 10 15:02:17 2025
$end
$version
	Icarus Verilog
$end
$timescale
	1s
$end
$scope module multiplexer_8_to_1_tb $end
$var wire 1 ! out $end
$var reg 8 " A [7:0] $end
$var reg 192 # name [191:0] $end
$var reg 3 $ sel [2:0] $end
$upscope $end
$enddefinitions $end
#0
$dumpvars
b0 $
b10010110111010101101110011101110110000101110010001000000100000101110010011100000110100101110100001000000101001101101001011011100110011101101000001000000011001000110010001100010011100000110101 #
b11001010 "
0!
$end
#10
1!
b1 $
#20
0!
b10 $
#30
1!
b11 $
#40
0!
b100 $
#50
b101 $
#60
1!
b110 $
#70
b111 $
#80
b0 $
b110101 "
#90
0!
b1 $
#100
1!
b10 $
#110
0!
b11 $
#120
1!
b100 $
#130
b101 $
#140
0!
b110 $
#150
b111 $
