Assignment_2/.v files/assign2_problem4_priority_encoder_8_to_3.v
module priority_encoder_8_to_3(input [7:0] A, output reg [2:0] out,  output reg valid);
    always @(*) begin
        valid = |A;
        if (A[7])      out = 3'b111;
        else if (A[6]) out = 3'b110;
        else if (A[5]) out = 3'b101;
        else if (A[4]) out = 3'b100;
        else if (A[3]) out = 3'b011;
        else if (A[2]) out = 3'b010;
        else if (A[1]) out = 3'b001;
        else if (A[0]) out = 3'b000;
        else out = 3'bxxx;
    end
endmodule

Assignment_2/Testbench/assign2_problem4_priority_encoder_8_to_3_tb_small.v
module priority_encoder_8_to_3_tb_small;
    reg [7:0] A;
    wire [2:0] out;
    wire valid;
    reg[8*24-1:0] name;
    integer i;
    priority_encoder_8_to_3 dut (.A(A), .out(out), .valid(valid));

    initial begin
        name = " Kunwar Arpit Singh 22185";
        $display("Kunwar Arpit Singh");
        $dumpfile("assign2_problem4_priority_encoder_8_to_3_small.vcd");
        $dumpvars(1, priority_encoder_8_to_3_tb_small);
        $display("Kunwar Arpit Singh");
        $display("Outputs for Single Active Inputs");
        $display("A(Input)  |   out(Output)    |    Valid");
        A = 8'b00000000; #10; $display("%b | %b | %b |", A, out, valid);
        A = 8'b00000001; #10; $display("%b | %b | %b |", A, out, valid); 
        A = 8'b00000010; #10; $display("%b | %b | %b |", A, out, valid); 
        A = 8'b00000100; #10; $display("%b | %b | %b |", A, out, valid);
        A = 8'b00001000; #10; $display("%b | %b | %b |", A, out, valid);
        A = 8'b00010000; #10; $display("%b | %b | %b |", A, out, valid);
        A = 8'b00100000; #10; $display("%b | %b | %b |", A, out, valid);
        A = 8'b01000000; #10; $display("%b | %b | %b |", A, out, valid);
        A = 8'b10000000; #10; $display("%b | %b | %b |", A, out, valid);
        
        $display("Outputs for Multiple Active Inputs");
        $display("A(Input)  |   out(Output)    |    Valid");
        A = 8'b00000001; #10; $display("%b | %b | %b |", A, out, valid); 
        A = 8'b00000011; #10; $display("%b | %b | %b |", A, out, valid); 
        A = 8'b00000110; #10; $display("%b | %b | %b |", A, out, valid);
        A = 8'b00001100; #10; $display("%b | %b | %b |", A, out, valid);
        A = 8'b00010001; #10; $display("%b | %b | %b |", A, out, valid);
        A = 8'b00101000; #10; $display("%b | %b | %b |", A, out, valid);
        A = 8'b01010000; #10; $display("%b | %b | %b |", A, out, valid);
        A = 8'b11111111; #10; $display("%b | %b | %b |", A, out, valid);
        $finish;
    end
endmodule

Assignment_2/vcd/assign2_problem4_priority_encoder_8_to_3_small.vcd
$date
	Wed Sep 10 16:33:16 2025
$end
$version
	Icarus Verilog
$end
$timescale
	1s
$end
$scope module priority_encoder_8_to_3_tb_small $end
$var wire 3 ! out [2:0] $end
$var wire 1 " valid $end
$var reg 8 # A [7:0] $end
$var reg 192 $ name [191:0] $end
$upscope $end
$enddefinitions $end
#0
$dumpvars
b10010110111010101101110011101110110000101110010001000000100000101110010011100000110100101110100001000000101001101101001011011100110011101101000001000000011001000110010001100010011100000110101 $
b0 #
0"
bx !
$end
#10
b0 !
b1 #
1"
#20
b1 !
b10 #
#30
b10 !
b100 #
#40
b11 !
b1000 #
#50
b100 !
b10000 #
#60
b101 !
b100000 #
#70
b110 !
b1000000 #
#80
b111 !
b10000000 #
#90
b0 !
b1 #
#100
b1 !
b11 #
#110
b10 !
b110 #
#120
b11 !
b1100 #
#130
b100 !
b10001 #
#140
b101 !
b101000 #
#150
b110 !
b1010000 #
#160
b111 !
b11111111 #
