Assignment_1/.v files/assign1_problem3_half_subtractor.v
module half_subtractor (input A, input B, output diff, output borrow_out);

    xor g1(diff, A, B);
    wire not_A;
    not g2(not_A, A);
    and g3(borrow_out, not_A, B);
endmodule

Assignment_1/.v files/assign1_problem3_full_subtractor.v
`include "assign1_problem3_half_subtractor.v"
module full_subtractor (input A, input B, input borrow_in, output diff, output borrow_out);
    
    wire diff1, borrow1, borrow2;

    half_subtractor hs1 (.A(A), .B(B), .diff(diff1), .borrow_out(borrow1));
    half_subtractor hs2 (.A(diff1), .B(borrow_in), .diff(diff), .borrow_out(borrow2));

    or g1(borrow_out, borrow1, borrow2);
    
endmodule

Assignment_1/Testbench/assign1_problem3_full_subtractor_tb.v
module full_subtractor_tb;

    reg A, B, borrow_in;
    wire diff, borrow_out;
    integer i;
    reg [8*24-1:0] name;

    full_subtractor dut (.A(A), .B(B), .borrow_in(borrow_in), .diff(diff), .borrow_out(borrow_out));

    initial begin
        name = " Kunwar Arpit Singh 22185";
        $display("Kunwar Arpit Singh");
        $dumpfile("assign1_problem3_full_subtractor.vcd");
        $dumpvars(1, full_subtractor_tb);

        $display(" A | B | borrow_in | diff | borrow_out");
        $display("---------------------------");

        for ( i = 0  ; i < 8; i = i + 1) begin
            {A, B, borrow_in} = i;
            #10;
            $display(" %b | %b |    %b     |  %b  |     %b", A, B, borrow_in, diff, borrow_out);
        end
        $finish;
    end
endmodule

Assignment_1/vcd/assign1_problem3_full_subtractor.vcd
$date
	Sun Sep 07 22:02:19 2025
$end
$version
	Icarus Verilog
$end
$timescale
	1s
$end
$scope module full_subtractor_tb $end
$var wire 1 ! borrow_out $end
$var wire 1 " diff $end
$var reg 1 # A $end
$var reg 1 $ B $end
$var reg 1 % borrow_in $end
$var integer 32 & i [31:0] $end
$var reg 192 ' name [191:0] $end
$upscope $end
$enddefinitions $end
#0
$dumpvars
b10010110111010101101110011101110110000101110010001000000100000101110010011100000110100101110100001000000101001101101001011011100110011101101000001000000011001000110010001100010011100000110101 '
b0 &
0%
0$
0#
0"
0!
$end
#10
1!
1"
1%
b1 &
#20
1"
1$
0%
b10 &
#30
0"
1%
b11 &
#40
0!
1"
1#
0$
0%
b100 &
#50
0"
1%
b101 &
#60
0"
1$
0%
b110 &
#70
1!
1"
1%
b111 &
#80
b1000 &
