Assignment_1/.v files/assign1_problem4_3_to_8_decoder.v
module decoder_3_to_8(input [2:0] d, output [7:0] y);

    wire d0_not, d1_not, d2_not;

    not (d0_not, d[0]);
    not (d1_not, d[1]);
    not (d2_not, d[2]);

    and (y[0], d0_not, d1_not, d2_not);
    and (y[1], d[0], d1_not, d2_not);
    and (y[2], d0_not, d[1], d2_not);
    and (y[3], d[0], d[1], d2_not);
    and (y[4], d0_not, d1_not, d[2]);
    and (y[5], d[0], d1_not, d[2]);
    and (y[6], d0_not, d[1], d[2]);
    and (y[7], d[0], d[1], d[2]);

endmodule

Assignment_1/Testbench/assign1_problem4_3_to_8_decoder_tb.v
module decoder_3_to_8_tb;
    reg[2:0] d;
    wire[7:0] y;
    reg [8*24-1:0] name;

    decoder_3_to_8 dut (d, y);

    initial begin
        name = " Kunwar Arpit Singh 22185";
        $display("Kunwar Arpit Singh");
        $dumpfile("assign1_problem4_3_to_8_decoder.vcd");
        $dumpvars(1, decoder_3_to_8_tb);

        $display("d2 | d1 | d0 || y7 | y6 | y5 | y4 | y3 | y2 | y1 | y0");
        $display("-------------------------------");
        d = 3'b000; #10;
        $display("%b  | %b  | %b  || %b | %b | %b | %b | %b | %b | %b | %b", d[2], d[1], d[0], y[7], y[6], y[5], y[4], y[3], y[2], y[1], y[0]);
        d = 3'b001; #10;
        $display("%b  | %b  | %b  || %b | %b | %b | %b | %b | %b | %b | %b", d[2], d[1], d[0], y[7], y[6], y[5], y[4], y[3], y[2], y[1], y[0]);
        d = 3'b010; #10;
        $display("%b  | %b  | %b  || %b | %b | %b | %b | %b | %b | %b | %b", d[2], d[1], d[0], y[7], y[6], y[5], y[4], y[3], y[2], y[1], y[0]);
        d = 3'b011; #10;
        $display("%b  | %b  | %b  || %b | %b | %b | %b | %b | %b | %b | %b", d[2], d[1], d[0], y[7], y[6], y[5], y[4], y[3], y[2], y[1], y[0]);
        d = 3'b100; #10;
        $display("%b  | %b  | %b  || %b | %b | %b | %b | %b | %b | %b | %b", d[2], d[1], d[0], y[7], y[6], y[5], y[4], y[3], y[2], y[1], y[0]);
        d = 3'b101; #10;
        $display("%b  | %b  | %b  || %b | %b | %b | %b | %b | %b | %b | %b", d[2], d[1], d[0], y[7], y[6], y[5], y[4], y[3], y[2], y[1], y[0]);
        d = 3'b110; #10;
        $display("%b  | %b  | %b  || %b | %b | %b | %b | %b | %b | %b | %b", d[2], d[1], d[0], y[7], y[6], y[5], y[4], y[3], y[2], y[1], y[0]);
        d = 3'b111; #10;
        $display("%b  | %b  | %b  || %b | %b | %b | %b | %b | %b | %b | %b", d[2], d[1], d[0], y[7], y[6], y[5], y[4], y[3], y[2], y[1], y[0]);
    end
endmodule

Assignment_1/vcd/assign1_problem4_3_to_8_decoder.vcd
$date
	Mon Sep 08 00:10:25 2025
$end
$version
	Icarus Verilog
$end
$timescale
	1s
$end
$scope module decoder_3_to_8_tb $end
$var wire 1 ! y0 $end
$var wire 1 " y1 $end
$var wire 1 # y2 $end
$var wire 1 $ y3 $end
$var wire 1 % y4 $end
$var wire 1 & y5 $end
$var wire 1 ' y6 $end
$var wire 1 ( y7 $end
$var reg 1 ) d0 $end
$var reg 1 * d1 $end
$var reg 1 + d2 $end
$var reg 192 , name [191:0] $end
$upscope $end
$enddefinitions $end
#0
$dumpvars
b10010110111010101101110011101110110000101110010001000000100000101110010011100000110100101110100001000000101001101101001011011100110011101101000001000000011001000110010001100010011100000110101 ,
0+
0*
0)
0(
0'
0&
0%
0$
0#
0"
1!
$end
#10
0!
1"
1)
#20
1#
0"
1*
0)
#30
0#
1$
1)
#40
1%
0$
1+
0*
0)
#50
0%
1&
1)
#60
1'
0&
1*
0)
#70
0'
1(
1)
