Assignment_1/.v files/assign1_problem2_4_bit_comparator.v
module comparator_1_bit(input A, input B, output eq, output gt, output lt);
    xnor(eq, A, B);
    and(gt, A, ~B);
    and(lt, ~A, B);
endmodule

module comparator_4_bit(input [3:0] A, input [3:0] B, output a_eq_b, output a_gt_b, output a_lt_b);
    wire [3:0] eq, gt, lt;

    comparator_1_bit comp0(A[0], B[0], eq[0], gt[0], lt[0]);
    comparator_1_bit comp1(A[1], B[1], eq[1], gt[1], lt[1]);
    comparator_1_bit comp2(A[2], B[2], eq[2], gt[2], lt[2]);
    comparator_1_bit comp3(A[3], B[3], eq[3], gt[3], lt[3]);

    assign a_eq_b = eq[0] & eq[1] & eq[2] & eq[3];
    assign a_gt_b = gt[0] | (eq[0] & gt[1]) | (eq[0] & eq[1] & gt[2]) | (eq[0] & eq[1] & eq[2] & gt[3]);
    assign a_lt_b = lt[0] | (eq[0] & lt[1]) | (eq[0] & eq[1] & lt[2]) | (eq[0] & eq[1] & eq[2] & lt[3]);
endmodule

Assignment_1/Testbench/assign1_problem2_4_bit_comparator_tb.v
module comparator_4_bit_tb;
    reg [3:0] A, B;
    wire a_eq_b;
    wire a_gt_b;
    wire a_lt_b;
    integer i, j;
    comparator_4_bit dut (.A(A), .B(B), .a_eq_b(a_eq_b), .a_gt_b(a_gt_b), .a_lt_b(a_lt_b));
    reg [8*24-1:0] name;
    
    initial begin
        name = " Kunwar Arpit Singh 22185";
        $display("Kunwar Arpit Singh");
        $dumpfile("assign1_problem2_comparator_4_bit.vcd");
        $dumpvars(1, comparator_4_bit_tb);

        $display("Kunwar Arpit Singh");
        $display("A    | B     | A == B | A > B | A < B");
        $display("-----------------------");

        for (i = 0 ; i < 16 ; i = i+1) begin
            for (j = 0 ; j < 16 ; j = j+1) begin
                A = i;
                B = j;
                #10;
                $display("%b | %b |   %b |   %b |   %b", A, B, a_eq_b, a_gt_b, a_lt_b);
            end
        end
    end
endmodule

Assignment_1/vcd/assign1_problem2_comparator_4_bit.vcd
$date
	Mon Sep 08 10:51:36 2025
$end
$version
	Icarus Verilog
$end
$timescale
	1s
$end
$scope module comparator_4_bit_tb $end
$var wire 1 ! a_eq_b $end
$var wire 1 " a_gt_b $end
$var wire 1 # a_lt_b $end
$var reg 4 $ A [3:0] $end
$var reg 4 % B [3:0] $end
$var integer 32 & i [31:0] $end
$var integer 32 ' j [31:0] $end
$var reg 192 ( name [191:0] $end
$upscope $end
$enddefinitions $end
#0
$dumpvars
b10010110111010101101110011101110110000101110010001000000100000101110010011100000110100101110100001000000101001101101001011011100110011101101000001000000011001000110010001100010011100000110101 (
b0 '
b0 &
b0 %
b0 $
0#
0"
1!
$end
#10
0!
1#
b1 %
b1 '
#20
b10 %
b10 '
#30
b11 %
b11 '
#40
b100 %
b100 '
#50
b101 %
b101 '
#60
b110 %
b110 '
#70
b111 %
b111 '
#80
b1000 %
b1000 '
#90
b1001 %
b1001 '
#100
b1010 %
b1010 '
#110
b1011 %
b1011 '
#120
b1100 %
b1100 '
#130
b1101 %
b1101 '
#140
b1110 %
b1110 '
#150
b1111 %
b1111 '
#160
1"
0#
b0 %
b1 $
b1 &
b0 '
#170
0"
1!
b1 %
b1 '
#180
1"
0!
b10 %
b10 '
#190
1#
0"
b11 %
b11 '
#200
1"
0#
b100 %
b100 '
#210
1#
0"
b101 %
b101 '
#220
1"
0#
b110 %
b110 '
#230
1#
0"
b111 %
b111 '
#240
1"
0#
b1000 %
b1000 '
#250
1#
0"
b1001 %
b1001 '
#260
1"
0#
b1010 %
b1010 '
#270
1#
0"
b1011 %
b1011 '
#280
1"
0#
b1100 %
b1100 '
#290
1#
0"
b1101 %
b1101 '
#300
1"
0#
b1110 %
b1110 '
#310
1#
0"
b1111 %
b1111 '
#320
1"
0#
b0 %
b10 $
b10 &
b0 '
#330
0"
1#
b1 %
b1 '
#340
0#
1!
b10 %
b10 '
#350
0!
1#
b11 %
b11 '
#360
1"
0#
b100 %
b100 '
#370
0"
1#
b101 %
b101 '
#380
b110 %
b110 '
#390
b111 %
b111 '
#400
1"
0#
b1000 %
b1000 '
#410
0"
1#
b1001 %
b1001 '
#420
b1010 %
b1010 '
#430
b1011 %
b1011 '
#440
1"
0#
b1100 %
b1100 '
#450
0"
1#
b1101 %
b1101 '
#460
b1110 %
b1110 '
#470
b1111 %
b1111 '
#480
1"
0#
b0 %
b11 $
b11 &
b0 '
#490
b1 %
b1 '
#500
b10 %
b10 '
#510
0"
1!
b11 %
b11 '
#520
1"
0#
0!
b100 %
b100 '
#530
b101 %
b101 '
#540
b110 %
b110 '
#550
1#
0"
b111 %
b111 '
#560
1"
0#
b1000 %
b1000 '
#570
b1001 %
b1001 '
#580
b1010 %
b1010 '
#590
1#
0"
b1011 %
b1011 '
#600
1"
0#
b1100 %
b1100 '
#610
b1101 %
b1101 '
#620
b1110 %
b1110 '
#630
1#
0"
b1111 %
b1111 '
#640
1"
0#
b0 %
b100 $
b100 &
b0 '
#650
0"
1#
b1 %
b1 '
#660
b10 %
b10 '
#670
b11 %
b11 '
#680
0#
1!
b100 %
b100 '
#690
0!
1#
b101 %
b101 '
#700
b110 %
b110 '
#710
b111 %
b111 '
#720
1"
0#
b1000 %
b1000 '
#730
0"
1#
b1001 %
b1001 '
#740
b1010 %
b1010 '
#750
b1011 %
b1011 '
#760
b1100 %
b1100 '
#770
b1101 %
b1101 '
#780
b1110 %
b1110 '
#790
b1111 %
b1111 '
#800
1"
0#
b0 %
b101 $
b101 &
b0 '
#810
b1 %
b1 '
#820
b10 %
b10 '
#830
1#
0"
b11 %
b11 '
#840
1"
0#
b100 %
b100 '
#850
0"
1!
b101 %
b101 '
#860
1"
0!
b110 %
b110 '
#870
1#
0"
b111 %
b111 '
#880
1"
0#
b1000 %
b1000 '
#890
b1001 %
b1001 '
#900
b1010 %
b1010 '
#910
1#
0"
b1011 %
b1011 '
#920
1"
0#
b1100 %
b1100 '
#930
1#
0"
b1101 %
b1101 '
#940
1"
0#
b1110 %
b1110 '
#950
1#
0"
b1111 %
b1111 '
#960
1"
0#
b0 %
b110 $
b110 &
b0 '
#970
0"
1#
b1 %
b1 '
#980
1"
0#
b10 %
b10 '
#990
0"
1#
b11 %
b11 '
#1000
1"
0#
b100 %
b100 '
#1010
0"
1#
b101 %
b101 '
#1020
0#
1!
b110 %
b110 '
#1030
0!
1#
b111 %
b111 '
#1040
1"
0#
b1000 %
b1000 '
#1050
0"
1#
b1001 %
b1001 '
#1060
1"
0#
b1010 %
b1010 '
#1070
0"
1#
b1011 %
b1011 '
#1080
1"
0#
b1100 %
b1100 '
#1090
0"
1#
b1101 %
b1101 '
#1100
b1110 %
b1110 '
#1110
b1111 %
b1111 '
#1120
1"
0#
b0 %
b111 $
b111 &
b0 '
#1130
b1 %
b1 '
#1140
b10 %
b10 '
#1150
b11 %
b11 '
#1160
0!
b100 %
b100 '
#1170
b101 %
b101 '
#1180
b110 %
b110 '
#1190
0"
1!
b111 %
b111 '
#1200
1"
0#
0!
b1000 %
b1000 '
#1210
b1001 %
b1001 '
#1220
b1010 %
b1010 '
#1230
b1011 %
b1011 '
#1240
0#
b1100 %
b1100 '
#1250
b1101 %
b1101 '
#1260
b1110 %
b1110 '
#1270
1#
0"
b1111 %
b1111 '
#1280
1"
0#
b0 %
b1000 $
b1000 &
b0 '
#1290
0"
1#
b1 %
b1 '
#1300
b10 %
b10 '
#1310
b11 %
b11 '
#1320
b100 %
b100 '
#1330
b101 %
b101 '
#1340
b110 %
b110 '
#1350
b111 %
b111 '
#1360
0#
1!
b1000 %
b1000 '
#1370
0!
1#
b1001 %
b1001 '
#1380
b1010 %
b1010 '
#1390
b1011 %
b1011 '
#1400
b1100 %
b1100 '
#1410
b1101 %
b1101 '
#1420
b1110 %
b1110 '
#1430
b1111 %
b1111 '
#1440
1"
0#
b0 %
b1001 $
b1001 &
b0 '
#1450
b1 %
b1 '
#1460
b10 %
b10 '
#1470
1#
0"
b11 %
b11 '
#1480
1"
0#
b100 %
b100 '
#1490
1#
0"
b101 %
b101 '
#1500
1"
0#
b110 %
b110 '
#1510
1#
0"
b111 %
b111 '
#1520
1"
0#
b1000 %
b1000 '
#1530
0"
1!
b1001 %
b1001 '
#1540
1"
0!
b1010 %
b1010 '
#1550
1#
0"
b1011 %
b1011 '
#1560
1"
0#
b1100 %
b1100 '
#1570
1#
0"
b1101 %
b1101 '
#1580
1"
0#
b1110 %
b1110 '
#1590
1#
0"
b1111 %
b1111 '
#1600
1"
0#
b0 %
b1010 $
b1010 &
b0 '
#1610
0"
1#
b1 %
b1 '
#1620
1"
0#
b10 %
b10 '
#1630
0"
1#
b11 %
b11 '
#1640
1"
0#
b100 %
b100 '
#1650
0"
1#
b101 %
b101 '
#1660
b110 %
b110 '
#1670
b111 %
b111 '
#1680
1"
0#
b1000 %
b1000 '
#1690
0"
1#
b1001 %
b1001 '
#1700
0#
1!
b1010 %
b1010 '
#1710
0!
1#
b1011 %
b1011 '
#1720
1"
0#
b1100 %
b1100 '
#1730
0"
1#
b1101 %
b1101 '
#1740
b1110 %
b1110 '
#1750
b1111 %
b1111 '
#1760
1"
0#
b0 %
b1011 $
b1011 &
b0 '
#1770
b1 %
b1 '
#1780
b10 %
b10 '
#1790
b11 %
b11 '
#1800
1"
0#
b100 %
b100 '
#1810
b101 %
b101 '
#1820
b110 %
b110 '
#1830
1#
0"
b111 %
b111 '
#1840
1"
0#
0!
b1000 %
b1000 '
#1850
b1001 %
b1001 '
#1860
b1010 %
b1010 '
#1870
0"
1!
b1011 %
b1011 '
#1880
1"
0#
0!
b1100 %
b1100 '
#1890
b1101 %
b1101 '
#1900
b1110 %
b1110 '
#1910
1#
0"
b1111 %
b1111 '
#1920
1"
0#
b0 %
b1100 $
b1100 &
b0 '
#1930
0"
1#
b1 %
b1 '
#1940
b10 %
b10 '
#1950
b11 %
b11 '
#1960
1"
0#
b100 %
b100 '
#1970
0"
1#
b101 %
b101 '
#1980
b110 %
b110 '
#1990
b111 %
b111 '
#2000
1"
0#
b1000 %
b1000 '
#2010
0"
1#
b1001 %
b1001 '
#2020
b1010 %
b1010 '
#2030
b1011 %
b1011 '
#2040
0#
1!
b1100 %
b1100 '
#2050
0!
1#
b1101 %
b1101 '
#2060
b1110 %
b1110 '
#2070
b1111 %
b1111 '
#2080
1"
0#
b0 %
b1101 $
b1101 &
b0 '
#2090
b1 %
b1 '
#2100
b10 %
b10 '
#2110
1#
0"
b11 %
b11 '
#2120
1"
0#
b100 %
b100 '
#2130
b101 %
b101 '
#2140
b110 %
b110 '
#2150
1#
0"
b111 %
b111 '
#2160
1"
0#
b1000 %
b1000 '
#2170
b1001 %
b1001 '
#2180
b1010 %
b1010 '
#2190
1#
0"
b1011 %
b1011 '
#2200
1"
0#
b1100 %
b1100 '
#2210
0"
1!
b1101 %
b1101 '
#2220
1"
0!
b1110 %
b1110 '
#2230
1#
0"
b1111 %
b1111 '
#2240
1"
0#
b0 %
b1110 $
b1110 &
b0 '
#2250
0"
1#
b1 %
b1 '
#2260
1"
0#
b10 %
b10 '
#2270
0"
1#
b11 %
b11 '
#2280
1"
0#
b100 %
b100 '
#2290
0"
1#
b101 %
b101 '
#2300
1"
0#
b110 %
b110 '
#2310
0"
1#
b111 %
b111 '
#2320
1"
0#
b1000 %
b1000 '
#2330
0"
1#
b1001 %
b1001 '
#2340
1"
0#
b1010 %
b1010 '
#2350
0"
1#
b1011 %
b1011 '
#2360
1"
0#
b1100 %
b1100 '
#2370
0"
1#
b1101 %
b1101 '
#2380
0#
1!
b1110 %
b1110 '
#2390
0!
1#
b1111 %
b1111 '
#2400
1"
0#
b0 %
b1111 $
b1111 &
b0 '
#2410
b1 %
b1 '
#2420
b10 %
b10 '
#2430
b11 %
b11 '
#2440
b100 %
b100 '
#2450
b101 %
b101 '
#2460
b110 %
b110 '
#2470
b111 %
b111 '
#2480
1"
0!
b1000 %
b1000 '
#2490
b1001 %
b1001 '
#2500
b1010 %
b1010 '
#2510
b1011 %
b1011 '
#2520
0!
b1100 %
b1100 '
#2530
b1101 %
b1101 '
#2540
b1110 %
b1110 '
#2550
0"
1!
b1111 %
b1111 '
#2560
b10000 &
b10000 '
