Assignment_1/.v files/assign1_problem1_and.v
module and_gate_3_input (input A, input B, input C, output Y);
    wire w1;
    and g1(w1, A, B);
    and g2(Y, w1, C);
endmodule

Assignment_1/Testbench/assign1_problem1_and_tb.v
module and_gate_3_input_tb;
    reg A, B, C;
    wire Y;
    reg [8*24-1:0] name;

    and_gate_3_input dut (.A(A), .B(B), .C(C), .Y(Y));

    initial begin
        name = " Kunwar Arpit Singh 22185";
        $dumpfile("assign1_problem1_and_gate_3_input.vcd");
        $dumpvars(1, and_gate_3_input_tb);

        $display("Kunwar Arpit Singh");
        $display("A | B | C | Y");
        $display("-----------------");

        A = 0; B = 0; C = 0; #10;
        $display("%b | %b | %b | %b", A, B, C, Y);

        A = 0; B = 0; C = 1; #10;
        $display("%b | %b | %b | %b", A, B, C, Y);

        A = 0; B = 1; C = 0; #10;
        $display("%b | %b | %b | %b", A, B, C, Y);

        A = 0; B = 1; C = 1; #10;
        $display("%b | %b | %b | %b", A, B, C, Y);

        A = 1; B = 0; C = 0; #10;
        $display("%b | %b | %b | %b", A, B, C, Y);

        A = 1; B = 0; C = 1; #10;
        $display("%b | %b | %b | %b", A, B, C, Y);

        A = 1; B = 1; C = 0; #10;
        $display("%b | %b | %b | %b", A, B, C, Y);

        A = 1; B = 1; C = 1; #10;
        $display("%b | %b | %b | %b", A, B, C, Y);

        $finish;
    end
endmodule

Assignment_1/vcd/assign1_problem1_and_gate_3_input.vcd
$date
	Sun Sep 07 21:22:35 2025
$end
$version
	Icarus Verilog
$end
$timescale
	1s
$end
$scope module and_gate_3_input_tb $end
$var wire 1 ! Y $end
$var reg 1 " A $end
$var reg 1 # B $end
$var reg 1 $ C $end
$var reg 192 % name [191:0] $end
$upscope $end
$enddefinitions $end
#0
$dumpvars
b10010110111010101101110011101110110000101110010001000000100000101110010011100000110100101110100001000000101001101101001011011100110011101101000001000000011001000110010001100010011100000110101 %
0$
0#
0"
0!
$end
#10
1$
#20
0$
1#
#30
1$
#40
0$
0#
1"
#50
1$
#60
0$
1#
#70
1!
1$
