Assignment_1/.v files/assign1_problem4_4_to_1_multiplexer.v
module mux_4_to_1(input [3:0] d_in, input[1:0] s, output y);
    wire s0_not, s1_not;
    wire w0, w1, w2, w3;

    not(s0_not, s[0]);
    not(s1_not, s[1]);

    and(w0, d_in[0], s0_not, s1_not);
    and(w1, d_in[1], s[0], s1_not);
    and(w2, d_in[2], s0_not, s[1]);
    and(w3, d_in[3], s[0], s[1]);

    or(y, w0, w1, w2, w3);

endmodule

Assignment_1/Testbench/assign1_problem4_4_to_1_multiplexer_tb.v
module mux_4_to_1_tb;
    reg [3:0] d_in;
    reg [1:0] s;
    wire y;
    reg [8*24-1:0] name;

    mux_4_to_1 dut(.d_in(d_in), .s(s), .y(y));

    initial begin
        name = " Kunwar Arpit Singh 22185";
        $display("Kunwar Arpit Singh");
        $dumpfile("assign1_problem4_mux_4_to_1.vcd");
        $dumpvars(1, mux_4_to_1_tb);

        d_in = 4'b1010;

        $display("s1 | s0 | y (selected data)");
        $display("-----------------------");

        s = 2'b00; #10;
        $display(" %b | %b |  %b (d0)", s[1], s[0], y);

        s = 2'b01; #10;
        $display(" %b | %b |  %b (d1)", s[1], s[0], y);

        s = 2'b10; #10;
        $display(" %b | %b |  %b (d2)", s[1], s[0], y);

        s = 2'b11; #10;
        $display(" %b | %b |  %b (d3)", s[1], s[0], y);

        d_in = 4'b0101;

        $display("s1 | s0 | y (selected data)");
        $display("-----------------------");

        s = 2'b00; #10;
        $display(" %b | %b |  %b (d0)", s[1], s[0], y);

        s = 2'b01; #10;
        $display(" %b | %b |  %b (d1)", s[1], s[0], y);

        s = 2'b10; #10;
        $display(" %b | %b |  %b (d2)", s[1], s[0], y);

        s = 2'b11; #10;
        $display(" %b | %b |  %b (d3)", s[1], s[0], y);

        d_in = 4'b1111;

        $display("s1 | s0 | y (selected data)");
        $display("-----------------------");

        s = 2'b00; #10;
        $display(" %b | %b |  %b (d0)", s[1], s[0], y);

        s = 2'b01; #10;
        $display(" %b | %b |  %b (d1)", s[1], s[0], y);

        s = 2'b10; #10;
        $display(" %b | %b |  %b (d2)", s[1], s[0], y);

        s = 2'b11; #10;
        $display(" %b | %b |  %b (d3)", s[1], s[0], y);

        $finish;
    end
endmodule

Assignment_1/vcd/assign1_problem4_mux_4_to_1.vcd
$date
	Mon Sep 08 10:08:32 2025
$end
$version
	Icarus Verilog
$end
$timescale
	1s
$end
$scope module mux_4_to_1_tb $end
$var wire 1 ! y $end
$var reg 4 " d_in [3:0] $end
$var reg 192 # name [191:0] $end
$var reg 2 $ s [1:0] $end
$upscope $end
$enddefinitions $end
#0
$dumpvars
b0 $
b10010110111010101101110011101110110000101110010001000000100000101110010011100000110100101110100001000000101001101101001011011100110011101101000001000000011001000110010001100010011100000110101 #
b1010 "
0!
$end
#10
1!
b1 $
#20
0!
b10 $
#30
1!
b11 $
#40
1!
b0 $
b101 "
#50
0!
b1 $
#60
1!
b10 $
#70
0!
b11 $
#80
1!
b0 $
b1111 "
#90
b1 $
#100
1!
b10 $
#110
b11 $
